.gitignore
LICENSE
README.md
chat.png
image.png
requirements.txt
setup.py
src/yaoc/__init__.py
src/yaoc/openai_cli.py
src/yaoc/tools.py
src/yaoc.egg-info/PKG-INFO
src/yaoc.egg-info/SOURCES.txt
src/yaoc.egg-info/dependency_links.txt
src/yaoc.egg-info/entry_points.txt
src/yaoc.egg-info/requires.txt
src/yaoc.egg-info/top_level.txt