Metadata-Version: 2.4
Name: yaoc
Version: 0.1.11
Summary: Yet Another OpenAI-compatible CLI
Home-page: https://github.com/doryiii/yaoc
Author: Dory
Author-email: dory@dory.moe
License: GPL-3.0-only
Classifier: Programming Language :: Python :: 3
Classifier: Operating System :: OS Independent
Requires-Python: >=3.6
License-File: LICENSE
Requires-Dist: requests
Requires-Dist: termcolor
Requires-Dist: rich
Requires-Dist: html2text
Requires-Dist: pydantic
Dynamic: author
Dynamic: author-email
Dynamic: classifier
Dynamic: description
Dynamic: description-content-type
Dynamic: home-page
Dynamic: license
Dynamic: license-file
Dynamic: requires-dist
Dynamic: requires-python
Dynamic: summary
